diskcollections/__init__.py
diskcollections/interfaces.py
diskcollections/py2to3.py
diskcollections/serializers.py
diskcollections/iterables/__init__.py
diskcollections/iterables/clients.py
diskcollections/iterables/iterables.py
python_disk_collections-0.1.0.dist-info/METADATA
python_disk_collections-0.1.0.dist-info/WHEEL
python_disk_collections-0.1.0.dist-info/licenses/LICENSE
python_disk_collections-0.1.0.dist-info/RECORD
