Metadata-Version: 2.4
Name: python-disk-collections
Version: 0.1.0
Summary: Module contains class with extended python list that stores items at disk.
Project-URL: Repository, https://github.com/thegrymek/python-disk-collections
Project-URL: Releases, https://github.com/thegrymek/python-disk-collections/releases
Author-email: Andrzej <6695650+thegrymek@users.noreply.github.com>
License: MIT
License-File: LICENSE
Keywords: cache,collections,deque,disk,json,list,pickle,zlib
Classifier: Operating System :: OS Independent
Classifier: Programming Language :: Python :: 3.8
Classifier: Programming Language :: Python :: 3.9
Classifier: Programming Language :: Python :: 3.10
Classifier: Programming Language :: Python :: 3.11
Classifier: Programming Language :: Python :: 3.12
Classifier: Programming Language :: Python :: 3.13
Classifier: Topic :: Software Development :: Libraries :: Python Modules
Requires-Python: <4.0,>=3.8
